setup.py
awsnapshots/__init__.py
awsnapshots/__main__.py
awsnapshots/snapshots.py
awsnapshots.egg-info/PKG-INFO
awsnapshots.egg-info/SOURCES.txt
awsnapshots.egg-info/dependency_links.txt
awsnapshots.egg-info/not-zip-safe
awsnapshots.egg-info/requires.txt
awsnapshots.egg-info/top_level.txt
bin/awsnapshots