Metadata-Version: 1.0
Name: awsnapshots
Version: 0.1.1
Summary: Simple tool to manage AWS Volume Snapshots using the AWS API
Home-page: http://github.com/jrhames/AWSnapshots
Author: Jr. Hames
Author-email: jr@hames.com.br
License: MIT
Platform: UNKNOWN
